tap_pivotal_tracker/__init__.py
tap_pivotal_tracker/client.py
tap_pivotal_tracker/version.py
tap_pivotal_tracker/schemas/accounts.json
tap_pivotal_tracker/schemas/labels.json
tap_pivotal_tracker/schemas/project_memberships.json
tap_pivotal_tracker/schemas/projects.json
tap_pivotal_tracker/schemas/stories.json
tap_pivotal_tracker-0.1.1.dist-info/LICENSE
tap_pivotal_tracker-0.1.1.dist-info/METADATA
tap_pivotal_tracker-0.1.1.dist-info/WHEEL
tap_pivotal_tracker-0.1.1.dist-info/entry_points.txt
tap_pivotal_tracker-0.1.1.dist-info/top_level.txt
tap_pivotal_tracker-0.1.1.dist-info/RECORD
